odoo/addons/pago_derechos_autoria/Readme.me
odoo/addons/pago_derechos_autoria/__init__.py
odoo/addons/pago_derechos_autoria/__manifest__.py
odoo/addons/pago_derechos_autoria/models/__init__.py
odoo/addons/pago_derechos_autoria/models/derechos_autoria.py
odoo/addons/pago_derechos_autoria/static/description/icon.png
odoo/addons/pago_derechos_autoria/views/derechos_autoria_boton_view.xml
odoo13_addon_pago_derechos_autoria-13.0.0.0.2.dist-info/METADATA
odoo13_addon_pago_derechos_autoria-13.0.0.0.2.dist-info/WHEEL
odoo13_addon_pago_derechos_autoria-13.0.0.0.2.dist-info/top_level.txt
odoo13_addon_pago_derechos_autoria-13.0.0.0.2.dist-info/RECORD
